enhanced_adb/__init__.py
enhanced_adb/_utils.py
enhanced_adb/command_line.py
enhanced_adb/aapt/__init__.py
enhanced_adb/aapt/aapt.py
enhanced_adb/analyze/__init__.py
enhanced_adb/analyze/analyze_catcher.py
enhanced_adb/apk_repo/__init__.py
enhanced_adb/apk_repo/repo.py
enhanced_adb/bin/AdbWinApi.dll
enhanced_adb/bin/AdbWinUsbApi.dll
enhanced_adb/bin/aapt
enhanced_adb/bin/aapt.exe
enhanced_adb/bin/aapt_darwin
enhanced_adb/bin/adb
enhanced_adb/bin/adb.exe
enhanced_adb/bin/fastboot.exe
enhanced_adb/bin/libwinpthread-1.dll
enhanced_adb/foo/__init__.py
enhanced_adb/foo/fooooo.py
enhanced_adb/inspect/__init__.py
enhanced_adb/inspect/inspect_result.py
enhanced_adb/inspect/inspecter.py
enhanced_adb/inspect/manifest_parser.py
enhanced_adb/inspect/output.py
enhanced_adb/res/permission.yml
enhanced_adb/res/res_string.yml
enhanced_adb/res/user.yml
enhanced_adb-0.0.6.dist-info/LICENSE
enhanced_adb-0.0.6.dist-info/METADATA
enhanced_adb-0.0.6.dist-info/WHEEL
enhanced_adb-0.0.6.dist-info/entry_points.txt
enhanced_adb-0.0.6.dist-info/top_level.txt
enhanced_adb-0.0.6.dist-info/RECORD
