Metadata-Version: 2.1
Name: enhanced-adb
Version: 0.0.6
Summary: enhancement adb
Home-page: https://bitbucket.org/royfu/enhanced-adb/src
Author: roy.fu
Author-email: fuzhongqing1995@gmail.com
License: UNKNOWN
Platform: UNKNOWN
Classifier: Programming Language :: Python :: 3
Classifier: Development Status :: 3 - Alpha
Classifier: License :: OSI Approved :: MIT License
Classifier: Operating System :: OS Independent
Requires-Python: >=3.6
Requires-Dist: whichcraft
Requires-Dist: rich
Requires-Dist: pyyaml
Requires-Dist: pysmb
